note_to_fhir/__init__.py
note_to_fhir/data_utils.py
note_to_fhir/fhir_client.py
note_to_fhir/parsers.py
note_to_fhir/evaluation/__init__.py
note_to_fhir/evaluation/resources.py
note_to_fhir/inference/score.py
note_to_fhir/templates/simple.py
healthsageai_note_to_fhir-0.1.dist-info/LICENSE
healthsageai_note_to_fhir-0.1.dist-info/METADATA
healthsageai_note_to_fhir-0.1.dist-info/WHEEL
healthsageai_note_to_fhir-0.1.dist-info/entry_points.txt
healthsageai_note_to_fhir-0.1.dist-info/top_level.txt
healthsageai_note_to_fhir-0.1.dist-info/RECORD
