Metadata-Version: 2.1
Name: healthsageai-note-to-fhir
Version: 0.1
Summary: HealthSage AI LLM - from clinical note to FHIR
Author-email: HealthSage AI <hello@healthsage.ai>
Maintainer-email: HealthSage AI <hello@healthsage.ai>
License: GNU AFFERO GENERAL PUBLIC LICENSE
Project-URL: Homepage, https://github.com/healthsageai/healthsageai-note-to-fhir
Project-URL: Bug Reports, https://github.com/healthsageai/healthsageai-note-to-fhir/issues
Project-URL: Source, https://github.com/healthsageai/healthsageai-note-to-fhir/
Keywords: NLP,machine learning,pytorch,fhir
Classifier: Development Status :: 3 - Alpha
Classifier: Intended Audience :: Developers
Classifier: Topic :: Software Development :: Build Tools
Classifier: License :: OSI Approved :: GNU Affero General Public License v3 or later (AGPLv3+)
Classifier: Programming Language :: Python :: 3
Classifier: Programming Language :: Python :: 3.9
Classifier: Programming Language :: Python :: 3.10
Classifier: Programming Language :: Python :: 3.11
Classifier: Programming Language :: Python :: 3 :: Only
Requires-Python: >=3.9
License-File: LICENSE
Provides-Extra: demo
Requires-Dist: requests ; extra == 'demo'
Requires-Dist: gradio ; extra == 'demo'
Provides-Extra: inference
Provides-Extra: training
Requires-Dist: torch ; extra == 'training'
Requires-Dist: pytorch-gpu ; extra == 'training'
